binance_bot/__init__.py
binance_bot/config.py
binance_bot/core.py
binance_bot/helpers.py
binance_bot/models/__init__.py
binance_bot/strategies/__init__.py
test/__init__.py
test/context.py
test/test_advanced.py
test/test_basic.py
binance_bot-0.1.1.dist-info/LICENSE.md
binance_bot-0.1.1.dist-info/METADATA
binance_bot-0.1.1.dist-info/WHEEL
binance_bot-0.1.1.dist-info/top_level.txt
binance_bot-0.1.1.dist-info/RECORD
