Metadata-Version: 2.1
Name: binance-bot
Version: 0.1.1
Summary: Binance Bot Trade
Home-page: https://google.com.vn
Author: Nguyen Doan Cuong
Author-email: cuongnd86@gmail.com
License: Copyright (c) 2016 The Python Packaging Authority (PyPA)        
Platform: UNKNOWN
License-File: LICENSE.md
